prmt/__init__.py
prmt-4.1.0.dist-info/LICENSE
prmt-4.1.0.dist-info/METADATA
prmt-4.1.0.dist-info/WHEEL
prmt-4.1.0.dist-info/RECORD
