Metadata-Version: 2.1
Name: prmt
Version: 4.1.0
Summary: Simple and robust command line prompts for most values
Home-page: https://github.com/feluxe/prmt
License: Apache-2.0
Keywords: command,line,prompt,user,input
Author: feluxe
Author-email: felix@meyerwolters.de
Maintainer: feluxe
Maintainer-email: felix@meyerwolters.de
Requires-Python: >=3.7,<4.0
Classifier: License :: OSI Approved :: Apache Software License
Classifier: Programming Language :: Python :: 3
Classifier: Programming Language :: Python :: 3.7
Classifier: Programming Language :: Python :: 3.8
Classifier: Programming Language :: Python :: 3.9
Classifier: Programming Language :: Python :: 3.10
Classifier: Programming Language :: Python :: 3.11
Classifier: Programming Language :: Python :: 3.12
Project-URL: Repository, https://github.com/feluxe/prmt
